Workbook

Sheet Master Requirements Tracker
B2: Nibbl AI — Master Requirements Tracker
B3: Mapped to the Master Document (Nibbl_Master_Requirements_Consistency_Final). Status as of 11 Oct 2026. One row per requirement. Completed = works end to end, tested and can be demonstrated; anything with a missing piece stays In Progress.
C4: TOTAL REQUIREMENTS | D4: COMPLETED | E4: IN PROGRESS | F4: IN REVIEW | G4: PLANNED | H4: COMPLETION RATE
C5: =COUNTA(D9:D158) -> 150 | D5: =COUNTIF(F9:F158,"Completed") -> 130 | E5: =COUNTIF(F9:F158,"In Progress") -> 13 | F5: =COUNTIF(F9:F158,"In Review") -> 2 | G5: =COUNTIF(F9:F158,"Planned") -> 5 | H5: =IF(C5>0,D5/C5,0) -> 0.86666667
C6: Master Document requirements | D6: Works end to end, tested, demoable | E6: Partly built — gap in Notes | F6: Waiting on a third party | G6: Not started yet | H6: Completed ÷ total
B8: # | C8: Master Document Section | D8: Master Requirement | E8: What Was Delivered | F8: Status | G8: Platform | H8: Mobile App | I8: Where to See It | J8: How to Test | K8: Open Items / Notes | L8: Evidence (screenshot / video link) | M8: Checklist Ref
B9: 1 | C9: Brand Dashboard Home | D9: Brand name in header and welcome message | E9: Brand name from Brand Settings. | F9: Completed | G9: Brand Dashboard | H9: — | I9: Dashboard | J9: Log in as a brand; check the welcome line. | M9: #1
B10: 2 | C10: Brand Dashboard Home | D10: Navigation includes Tag Generator and Plans | E10: Both in the sidebar. | F10: Completed | G10: Brand Dashboard | H10: — | I10: Sidebar | J10: Open both pages. | M10: #35, #37
B11: 3 | C11: Brand Dashboard Home | D11: Current plan shown once, linked to Plans | E11: Plan name in the header opens Plans. | F11: Completed | G11: Brand Dashboard | H11: — | I11: Header → Plan | J11: Click the plan name. | M11: #35
B12: 4 | C12: Brand Dashboard Home | D12: Available Funds in header, linked to Wallet | E12: Shows current Available Funds; opens Wallet. | F12: Completed | G12: Brand Dashboard | H12: — | I12: Header | J12: Click Available Funds. | M12: #1
B13: 5 | C13: Brand Dashboard Home | D13: Date range — default Last 30 Days, selectable | E13: Date range selector (7 / 30 / 90 days / 12 months) drives both snapshots and the Campaign Performance table. | F13: Completed | G13: Brand Dashboard + Backend / API | H13: — | I13: Dashboard → Date range | J13: Switch the range; snapshot titles and table results update. | M13: #1
B14: 6 | C14: Brand Dashboard Home | D14: Rebate snapshot: claims, redemptions, redemption rate, Total Brand Cost + cost per redemption | E14: As specified, no mini charts/badges. | F14: Completed | G14: Brand Dashboard | H14: — | I14: Dashboard | J14: Compare with Redemptions for 30 days. | M14: #1, #28
B15: 7 | C15: Brand Dashboard Home | D15: Review snapshot: invitations, completed, completion rate, Total Brand Cost + cost per review | E15: As specified. | F15: Completed | G15: Brand Dashboard | H15: — | I15: Dashboard | J15: Compare with Review Management. | M15: #1, #28
B16: 8 | C16: Brand Dashboard Home | D16: Campaign Performance table (incl. ended; type filter; spend; results) | E16: Rebate + review campaigns; results = claims / redemptions or invitations / completed reviews for the selected range. | F16: Completed | G16: Brand Dashboard + Backend / API | H16: — | I16: Dashboard → Campaign Performance | J16: Filter by type; check review results. | M16: #1
B17: 9 | C17: Product Library | D17: Page controls: product count + Add Product | E17: Count and Add Product button. | F17: Completed | G17: Brand Dashboard | H17: — | I17: Product Library | J17: Open Product Library. | M17: #2
B18: 10 | C18: Product Library | D18: Product cards: image, name/flavor/size, rating, category, Product ID, receipt alias count, Edit | E18: Cards with image, details, rating, Edit. | F18: In Progress | G18: Brand Dashboard | H18: — | I18: Product Library | J18: Compare a card with the Master mockup. | K18: Alias count on the card to confirm against the mockup. | M18: #2
B19: 11 | C19: Product Library | D19: Product identity: separate record per flavor/size with permanent Product ID | E19: Flavor, format, size fields; ID assigned on save. | F19: In Progress | G19: Brand Dashboard + Backend / API | H19: — | I19: Add / Edit Product | J19: Create two sizes of one product. | K19: Separate Unit and Pack Count fields from the mockup aren't built (size is one field). | M19: #2
B20: 12 | C20: Product Library | D20: Product description kept for AI review questions | E20: Description sent to the AI for review questions. | F20: Completed | G20: Brand Dashboard + Backend / API | H20: — | I20: Add / Edit Product | J20: Fill the description. | M20: #2, #24
B21: 13 | C21: Product Library | D21: Standardized, admin-managed categories; brands can request a category | E21: Category is free text today. | F21: Planned | G21: Brand Dashboard + Admin Dashboard | H21: — | I21: — | J21: — | K21: Admin category list + 'Request category' not built. | M21: —
B22: 14 | C22: Product Library | D22: Optional UPC / SKU | E22: SKU field stored. | F22: Completed | G22: Brand Dashboard | H22: — | I22: Add / Edit Product | J22: Enter a SKU and save. | M22: #2
B23: 15 | C23: Product Library | D23: Receipt matching aliases: retailer + receipt text + optional item code | E23: Aliases (receipt text) added on the product or saved in manual review. | F23: In Progress | G23: Brand Dashboard + Backend / API | H23: — | I23: Product → Aliases; Redemptions → review | J23: Add an alias and upload a matching receipt. | K23: Alias retailer and item code fields not built (text only). | M23: #2, #21
B24: 16 | C24: Product Library | D24: Clickable rating opens Review Management filtered to the product | E24: Rating links to filtered Review Management. | F24: Completed | G24: Brand Dashboard | H24: — | I24: Product details → rating | J24: Click a product rating. | M24: #3
B25: 17 | C25: Product Library | D25: Add Product: same single-page fields as Edit; ID assigned on save | E25: Same form for add and edit. | F25: Completed | G25: Brand Dashboard | H25: — | I25: Add Product | J25: Add a product. | M25: #2
B26: 18 | C26: Product Library | D26: Delete Product: type DELETE; history preserved | E26: Confirmation + archive keeps reviews/redemptions. | F26: Completed | G26: Brand Dashboard | H26: — | I26: Edit Product → Delete | J26: Delete with and without typing DELETE. | M26: #3
B27: 19 | C27: Rebate Campaigns List | D27: Status tabs with counts (Draft, Pending Review, Scheduled, Active, Paused, Changes Requested, Ended) | E27: Status tabs on the rebate list. | F27: Completed | G27: Brand Dashboard | H27: — | I27: Rebate Campaigns | J27: Switch tabs. | M27: #7
B28: 20 | C28: Rebate Campaigns List | D28: 'X of Y active campaigns used — Upgrade' banner | E28: Usage bar with plan name and Upgrade button to Plans. | F28: Completed | G28: Brand Dashboard | H28: — | I28: Rebate Campaigns | J28: Activate campaigns up to the limit; click Upgrade. | M28: #34
B29: 21 | C29: Rebate Campaigns List | D29: Campaign cards: image, claims, active claims, pending review, redemptions, rate, total spend, current cycle claims | E29: Cards with metrics and 'X of Y' current cycle. | F29: Completed | G29: Brand Dashboard | H29: — | I29: Rebate Campaigns | J29: Compare a card with its detail page. | M29: #4, #7
B30: 22 | C30: Create Rebate Campaign | D30: ① Basics: internal name, start/end, campaign image | E30: As specified. | F30: Completed | G30: Brand Dashboard | H30: — | I30: Rebate → Create | J30: Create a draft. | M30: #5
B31: 23 | C31: Create Rebate Campaign | D31: ② Eligible products (search, select, same-category check) | E31: Product search and selection. | F31: Completed | G31: Brand Dashboard | H31: — | I31: Rebate → Create | J31: Select 3 products. | M31: #5
B32: 24 | C32: Create Rebate Campaign | D32: ③ Offer setup: Free / BOGO Free / Buy 1 Get 1 50% / Buy X Get $Y | E32: All four with locked reward math. | F32: Completed | G32: Brand Dashboard + Backend / API | H32: — | I32: Rebate → Create | J32: Create one of each. | M32: #5
B33: 25 | C33: Create Rebate Campaign | D33: ④ Offer details & shopper wording (suggested, editable, 100/250 limits) + locked system rules | E33: Suggested wording + locked rules summary. | F33: Completed | G33: Brand Dashboard | H33: — | I33: Rebate → Create | J33: Edit the headline. | M33: #5
B34: 26 | C34: Create Rebate Campaign | D34: ⑤ Retailer availability, Request/Add Retailer, up to 3 Featured | E34: Directory, add retailer, featured. | F34: Completed | G34: Brand Dashboard | H34: — | I34: Rebate → Create | J34: Add a retailer; pick featured. | M34: #10
B35: 27 | C35: Create Rebate Campaign | D35: ⑥ Receipt eligibility: Any Retailer / Retailer Required | E35: Enforced on receipts; saved on claim. | F35: Completed | G35: Brand Dashboard + Backend / API | H35: — | I35: Rebate → Create | J35: Set Retailer Required; upload another store's receipt. | M35: #10
... B38: 30 | C38: Create Rebate Campaign | D38: Discovery geography (Nationwide / States / ZIP + radius) | E38: All three, multiple areas. | F38: Completed | G38: Brand Dashboard + Backend / API | H38: — | I38: Rebate → Create | J38: Set ZIP radius; test from outside it. | M38: #13
B39: 31 | C39: Create Rebate Campaign | D39: Meta Pixel tracking on/off (validated Pixel ID only) | E39: Per-campaign switch; Pixel from Settings. | F39: Completed | G39: Brand Dashboard + Shopper Website | H39: — | I39: Campaign page | J39: Turn tracking on. | K39: Pixel validation is a format check. | M39: #11
B40: 32 | C40: Create Rebate Campaign | D40: Live shopper preview (same data as published offer) | E40: Live preview in builder. | F40: Completed | G40: Brand Dashboard | H40: — | I40: Rebate → Create | J40: Edit and watch the preview. | M40: #5
B41: 33 | C41: Create Rebate Campaign | D41: Save Draft / Submit for Nibbl Review; revisions keep approved version live | E41: Full approval workflow. | F41: Completed | G41: Brand Dashboard + Admin Dashboard | H41: — | I41: Campaign page; Admin → Approvals | J41: Submit, request changes, approve. | M41: #7, #44
B42: 34 | C42: Create Rebate Campaign | D42: Existing reservation rule snapshot | E42: Each claim keeps its terms. | F42: Completed | G42: Backend / API | H42: — | I42: Backend | J42: Edit a live campaign; old claim unchanged. | M42: #8
B43: 35 | C43: Offer Type Inputs & Shopper Output | D43: Reward math per offer type, net eligible price, rounding; shopper output sources | E43: As specified. | F43: Completed | G43: Backend / API + Shopper Website | H43: — | I43: Website → offer page | J43: Compare offer page with campaign. | M43: #5
B44: 36 | C44: Campaign Detail Page | D44: ① Status · ② Summary + Preview Offer · ④ Performance · ⑤ Current cycle · ⑥ Review activity · ⑦ Actions | E44: All sections. | F44: Completed | G44: Brand Dashboard | H44: — | I44: Rebate → View Details | J44: Open a campaign. | M44: #7
B45: 37 | C45: Campaign Detail Page | D45: ③ Assets: URL, QR, Open Preview, Download QR (PNG + high-res), 'don't distribute until approved' | E45: URL, QR and download. | F45: Completed | G45: Brand Dashboard | H45: — | I45: Campaign page → Assets | J45: Download the QR. | M45: #15
B46: 38 | C46: Effect on Existing Reservations | D46: Campaign goes live; limit reached → Temporarily Unavailable; expired claims never restore capacity | E46: As specified. | F46: Completed | G46: Backend / API | H46: — | I46: Backend | J46: Fill capacity; claim shows unavailable. | M46: #4
B47: 39 | C47: Effect on Existing Reservations | D47: Reserved reward funding (reserve max, pay actual, return difference) | E47: As specified. | F47: Completed | G47: Backend / API | H47: — | I47: Wallet → Reserved Funds | J47: Claim and redeem; check the ledger. | M47: #9
B48: 40 | C48: Effect on Existing Reservations | D48: Only Nibbl admin may cancel an existing reservation, with a reason | E48: Admin → Shoppers → Claims & Reviews → Cancel claim: reason required; the claim closes, the brand's reserved funds return, and the cancel is audit-logged. Brands can't cancel claims. | F48: Completed | G48: Admin Dashboard + Backend / API | H48: — | I48: Admin → Shoppers → shopper → Claims & Reviews | J48: Cancel an open claim with a reason; the brand's Reserved Funds drop by that claim. | M48: —
B49: 41 | C49: Discovery | D49: Location before discovery (allow location or ZIP; never unfiltered; don't re-ask) | E49: Location gate, saved. | F49: Completed | G49: Shopper Website + Backend / API | H49: API ready — app developer to build/confirm | I49: Website → home | J49: Open signed out. | M49: #13
B50: 42 | C50: Discovery | D50: Geographic eligibility gate | E50: Only eligible campaigns shown. | F50: Completed | G50: Backend / API | H50: API ready — app developer to build/confirm | I50: Website → For You | J50: Change ZIP. | M50: #13
B51: 43 | C51: Discovery | D51: Ranking: Base CVR × Store Match × Brand Interest (admin values) | E51: As specified. | F51: Completed | G51: Backend / API + Admin Dashboard | H51: API ready — app developer to build/confirm | I51: Admin → Settings | J51: Change a multiplier. | M51: #14
B52: 44 | C52: Discovery | D52: Campaign cards on For You (not product cards), category tabs, up to 24 per category | E52: Campaign cards with category tabs. | F52: In Progress | G52: Shopper Website + Backend / API | H52: API ready — app developer to build/confirm | I52: Website → For You | J52: Browse a category. | K52: 24-per-category cap and 'N eligible products' line to confirm. | M52: #13
B53: 45 | C53: Discovery | D53: Retailer match = ranking boost; Any Retailer / Retailer Required verification (eligible / unclear → manual / ineligible) | E53: As specified. | F53: Completed | G53: Backend / API | H53: — | I53: Backend | J53: Upload receipts from different stores. | M53: #10, #19
B54: 46 | C54: Discovery | D54: Direct entry: QR / Meta ad / URL bypasses geography only | E54: As specified. | F54: Completed | G54: Shopper Website + Backend / API | H54: API ready — app developer to build/confirm | I54: Campaign URL | J54: Open in a private window. | M54: #15
B55: 47 | C55: Discovery | D55: Campaign-level suppression (never brand-wide) | E55: As specified. | F55: Completed | G55: Backend / API | H55: API ready — app developer to build/confirm | I55: Website → For You | J55: Claim one campaign of a brand. | M55: #16
B56: 48 | C56: Shopper Rebate Flow | D56: Campaign details: products + ratings, Where to Buy, receipt eligibility, max rebate, offer eligibility, Going fast, share, save, Claim | E56: Offer page with all items. | F56: Completed | G56: Shopper Website | H56: API ready — app developer to build/confirm | I56: Website → offer | J56: Open an offer; share and save. | M56: #5, #10
B57: 49 | C57: Shopper Rebate Flow | D57: Reserve Offer: prefill email/phone (collect if logged out), two required consents | E57: Both consents required. | F57: In Progress | G57: Shopper Website + Backend / API | H57: API ready — app developer to build/confirm | I57: Website → offer → Claim | J57: Claim without consents → pop-up. | K57: Logged-out shoppers must sign in first (Master allows collecting email/phone on this step). | M57: #17
B58: 50 | C58: Shopper Rebate Flow | D58: Confirm Reservation screen: slot X of 5, exact deadline, Confirm & Reserve (slot consumed only here) | E58: Slot use shown on Reserve Offer; separate Confirm screen with product, retailer, reward, exact deadline and resulting slot use. | F58: Completed | G58: Shopper Website + Backend / API | H58: API ready — app developer to build/confirm | I58: Website → offer → Continue → Confirm & Reserve | J58: Claim an offer; check the deadline is 7 days out. | M58: #18
B59: 51 | C59: Shopper Rebate Flow | D59: Reservation eligibility checked before a claim slot is consumed | E59: All checks (consent, slots, already claimed, cooldown, dates, capacity, funds) run before the slot is used. | F59: Completed | G59: Backend / API | H59: — | I59: Backend | J59: Covered by automated tests. | M59: #17, #18
B60: 52 | C60: Shopper Rebate Flow | D60: Active claim slots (5) — occupied until approval, final rejection or expiry | E60: As specified. | F60: Completed | G60: Backend / API | H60: API ready — app developer to build/confirm | I60: Website → My Rewards | J60: Claim to the limit. | M60: #18
B61: 53 | C61: Shopper Rebate Flow | D61: Return Action Prompt: carousel, Submit Receipt + time left, Save for Later, My Offers badge | E61: As specified. | F61: Completed | G61: Shopper Website | H61: API ready — app developer to build/confirm | I61: Website → home; header badge | J61: Claim, then return home.
B62: 54 | C62: Shopper Rebate Flow | D62: Rebate restriction pop-ups (10) | E62: All with own code; consent, slots, claimed, cooldown, one-time, not started, paused, capacity, funds; retailer shown on offer. | F62: In Progress | G62: Shopper Website + Backend / API | H62: API ready — app developer to build/confirm | I62: Website → offer → Claim | J62: Trigger each case. | K62: Align titles/buttons exactly with the Master pop-up mockup (e.g. 'Review & Accept', 'N days remaining', 'View Eligible Retailers'). | M62: #17, #18
B63: 55 | C63: Receipt Submission | D63: Submit inside the active campaign: requirements list, take/choose photo, review before submit, submitted state | E63: Per-claim flow: Receipt Requirements (from the claim's locked terms), Take / Choose Photo, Review Your Receipt, Receipt submitted. | F63: Completed | G63: Shopper Website + Backend / API | H63: API ready — app developer to build/confirm | I63: Website → My Rewards → Upload receipt | J63: Upload a receipt for a claim. | M63: #19
B64: 56 | C64: Receipt Validation & Routing | D64: Capture date/time, retailer, transaction no., item, qty, net price, tax, total; clear date/retailer fail → reject; uncertain → manual; unreadable → new photo | E64: As specified. | F64: Completed | G64: Backend / API | H64: — | I64: Backend | J64: Upload clear / unclear / wrong-date receipts. | K64: OCR = AI service. | M64: #19, #21
B65: 57 | C65: Receipt Validation & Routing | D65: Duplicate receipt + quantity allocation | E65: As specified. | F65: Completed | G65: Backend / API | H65: — | I65: Backend | J65: Upload the same receipt twice. | M65: #19
B66: 58 | C66: Receipt Outcomes | D66: One resubmission before the original deadline (deadline never restarts) | E66: First clear date/retailer rejection keeps the claim open with one resubmission; the second is final (claim closed, slot released). Purchase must be on or after the claim. | F66: Completed | G66: Backend / API + Shopper Website | H66: API ready — app developer to build/confirm | I66: Website → My Rewards → Upload receipt | J66: Upload a receipt dated before the claim, then another. | M66: #19
B67: 59 | C67: Receipt Outcomes | D67: Outcome messages: accepted, manual review, unreadable, date, retailer, final rejection | E67: Master outcome screens: Purchase verified, Manual review, We couldn't read it, Date / Retailer does not qualify (with one resubmission), Final rejection. | F67: Completed | G67: Shopper Website + Backend / API | H67: API ready — app developer to build/confirm | I67: Website → after submitting a receipt | J67: Trigger each outcome. | K67: In-app + email decision notifications are tracked in Notifications & Reminders. | M67: #19
B68: 60 | C68: Notifications & Reminders | D68: Receipt reminders 48h and 12h before the exact deadline | E68: As specified. | F68: Completed | G68: Backend / API | H68: API ready — app developer to build/confirm | I68: Shopper notifications | J68: Scheduled job sends both reminders. | M68: #20
B69: 61 | C69: Notifications & Reminders | D69: Reservation confirmation, receipt submitted, approval/rejection (in-app + email), claim expiration | E69: All five sent immediately in-app; approval and rejection also emailed (SES). | F69: Completed | G69: Backend / API + Shopper Website | H69: API ready — app developer to build/confirm | I69: Website → notifications; email | J69: Claim, upload, get approved/rejected, let a claim expire. | M69: #20
B70: 62 | C70: Notifications & Reminders | D70: Push notification delivery (FCM / APNs) | E70: Push is a placeholder today. | F70: In Review | G70: Backend / API | H70: API ready — app developer to build/confirm | I70: — | J70: — | K70: Waiting on client Firebase Workload Identity setup (EC2 role sent). | M70: —
B71: 63 | C71: Brand Manual Review | D71: ① Claim & customer (email visible on every plan) · ② Full receipt viewer (zoom/rotate/download) · ③ Locked requirements | E71: As specified. | F71: Completed | G71: Brand Dashboard | H71: — | I71: Redemptions → Review | J71: Open a pending receipt. | M71: #21
B72: 64 | C72: Brand Manual Review | D72: ④ Select line · ⑤ Confirm mapping + corrections (audit) · ⑥ Optional alias · ⑦ Calculated reward, rejection reasons, internal note | E72: As specified. | F72: Completed | G72: Brand Dashboard | H72: — | I72: Redemptions → Review | J72: Approve with alias; reject with reason. | M72: #21
B73: 65 | C73: Brand Redemptions Page | D73: ① Summary (pending, approved, rejected, total paid) · ② Status tabs · ⑤ Priority queue | E73: As specified. | F73: Completed | G73: Brand Dashboard | H73: — | I73: Redemptions | J73: Switch tabs. | M73: #21, #22
B74: 66 | C74: Brand Redemptions Page | D74: ③ Search & filters (campaign, product, status, submitted date) | E74: Search, campaign, product (via campaign products), status tabs, date range. | F74: Completed | G74: Brand Dashboard | H74: — | I74: Redemptions | J74: Filter by campaign and product. | M74: #21
B75: 67 | C75: Brand Redemptions Page | D75: ⑥ Pagination & Export CSV | E75: As specified. | F75: Completed | G75: Brand Dashboard | H75: — | I75: Redemptions → Export CSV | J75: Export. | M75: #21
B76: 68 | C76: Brand Redemptions Page | D76: Seven-day automatic approval (max reward, labelled, no alias, slot released) | E76: As specified. | F76: Completed | G76: Brand Dashboard + Backend / API | H76: — | I76: Redemptions | J76: Check countdown. | M76: #22
B77: 69 | C77: Review Management | D77: KPIs: total, pending 1–3★ response, average rating, review spend, cost per review | E77: All five KPIs; spend from the wallet ledger. | F77: Completed | G77: Brand Dashboard + Backend / API | H77: — | I77: Reviews → Review Management | J77: Compare spend with the Wallet ledger. | M77: #26
B78: 70 | C78: Review Management | D78: Tabs (All, Published, 7-Day Hold, Flagged, Removed) + date range | E78: Tabs with counts + date range + keyword search. | F78: Completed | G78: Brand Dashboard | H78: — | I78: Review Management | J78: Switch tabs. | M78: #26
B79: 71 | C79: Review Management | D79: Filters: rating, retailer, product, region | E79: All four (retailer from the receipt, region from the shopper's state). | F79: Completed | G79: Brand Dashboard + Backend / API | H79: — | I79: Review Management | J79: Filter by retailer and region. | M79: #26
B80: 72 | C80: Review Management | D80: Review details: answers, final text, receipt evidence + gating summary, customer contact for service recovery | E80: Side panel with answers, receipt, gating summary, masked email + copy. | F80: Completed | G80: Brand Dashboard + Backend / API | H80: — | I80: Review Management → review | J80: Open a review. | M80: #26, #33
B81: 73 | C81: Review Management | D81: Low-rating response: countdown, Contact Customer, Add Brand Response, Flag for Removal | E81: Live countdown, Contact Customer (email), response, flag. | F81: Completed | G81: Brand Dashboard | H81: — | I81: Review Management | J81: Open a 2★ held review. | M81: #26
B82: 74 | C82: Review Management | D82: Flag reasons per Master (wrong product, unrelated, spam/fraud, PII, profanity, prohibited claim, other) + audit | E82: Master's 7 reasons, 500-char details, audit log. | F82: Completed | G82: Brand Dashboard + Admin Dashboard | H82: — | I82: Review Management → Flag | J82: Flag a review. | M82: #26
... B84: 76 | C84: Create Review Campaign | D84: Basics (required image), eligible products, controls, locked rules & cost | E84: As specified. | F84: Completed | G84: Brand Dashboard | H84: — | I84: Reviews → Create | J84: Create a review campaign. | M84: #23
B85: 77 | C85: Create Review Campaign | D85: Brand question pool: add, suggest, Test Review Chat | E85: Add + suggest. | F85: In Progress | G85: Brand Dashboard | H85: — | I85: Review campaign page | J85: Add and suggest questions. | K85: 'Test Review Chat' not built. | M85: #23
B86: 78 | C86: Create Review Campaign | D86: Save Draft / Submit for Nibbl Review (published after review) | E86: Brands activate review campaigns directly. | F86: Planned | G86: Brand Dashboard + Admin Dashboard | H86: — | I86: — | J86: — | K86: Nibbl approval for review campaigns not built. | M86: #23
B87: 79 | C87: Create Review Campaign | D87: Live shopper preview (mobile) | E87: — | F87: Planned | G87: Brand Dashboard | H87: — | I87: — | J87: — | K87: Not built. | M87: #23
B88: 80 | C88: Shopper Review Opportunity | D88: My Offers: Review Rewards card (Claim $1, Save for Later) | E88: Review cards in the carousel and My Rewards. | F88: Completed | G88: Shopper Website | H88: API ready — app developer to build/confirm | I88: Website → My Rewards | J88: Get a receipt verified. | M88: #23
B89: 81 | C89: Shopper Review Opportunity | D89: Product Confirmed · Multiple Matches · Missing Consent · Share Your Voice | E89: — | F89: Planned | G89: Shopper Website | H89: API ready — app developer to build/confirm | I89: — | J89: — | K89: These screens aren't built on the website (chat opens directly). | M89: #23
B90: 82 | C90: Shopper Review Opportunity | D90: Developer rules: scan all lines, 0/1/many opportunities, cooldown per shopper+product, $1 reserve, no second verification | E90: As specified. | F90: Completed | G90: Backend / API | H90: — | I90: Backend | J90: Covered by automated tests. | M90: #25
B91: 83 | C91: AI Chat Review | D91: Product context loaded; rotating brand question; generated title & review; edit; regenerate; final approval; $1 at any rating | E91: As specified. | F91: Completed | G91: Shopper Website + Backend / API | H91: API ready — app developer to build/confirm | I91: Website → review chat | J91: Complete a review. | M91: #24
B92: 84 | C92: AI Chat Review | D92: Five adaptive product questions with suggested answer chips | E92: Fixed AI questions today. | F92: In Review | G92: Backend / API | H92: API ready — app developer to build/confirm | I92: — | J92: — | K92: Adaptive questions wait on the AI service endpoint; suggested-answer chips not built. | M92: #24
B93: 85 | C93: AI Chat Review | D93: Separate 'recommend' and 'purchase again' questions; title 100 / body 500 limits | E93: One combined recommend question. | F93: In Progress | G93: Shopper Website + Backend / API | H93: API ready — app developer to build/confirm | I93: Website → review chat | J93: Complete a review. | K93: Split recommend vs repurchase; enforce 100/500 character limits. | M93: #24
B94: 86 | C94: Ratings & Reviews Display | D94: Ratings per product in campaign details; all reviews with sorting; review details + brand response; helpful | E94: As specified. | F94: Completed | G94: Shopper Website + Backend / API | H94: API ready — app developer to build/confirm | I94: Website → offer → reviews | J94: Sort and mark helpful. | M94: #27
B95: 87 | C95: Ratings & Reviews Display | D95: Reviews overview: rating, breakdown, % recommend, % would buy again, AI summary (positives + improvement) | E95: Rating, breakdown, % recommend. | F95: In Progress | G95: Shopper Website + Backend / API | H95: API ready — app developer to build/confirm | I95: Website → offer → reviews | J95: Open an offer with reviews. | K95: '% would buy again' not built; AI summary waits on the AI service. | M95: #27
B96: 88 | C96: Brand Analytics | D96: Cost & Results · Customer & Conversion · Campaign Performance (25-hour cycles) | E96: As specified. | F96: Completed | G96: Brand Dashboard | H96: — | I96: Analytics | J96: Compare cost with the ledger. | M96: #28
B97: 89 | C97: Customers | D97: Summary, search & filters, download opted-in, integrations Coming Soon, consent withdrawal rule | E97: As specified. | F97: Completed | G97: Brand Dashboard | H97: — | I97: Customers | J97: Filter and download. | M97: #29
B98: 90 | C98: Customers | D98: Table: brand activity, site activity, open claims, cooldowns, last active, status | E98: Columns per Master: Customer, Contact, Brand Activity (claims / rebates / reviews), Site Activity (total claims / % completion / reviews), Open Claims, Cooldowns (days left), Last Active, Status (Active / Banned), View. Tabs: All, Open Claim, Active Cooldown, Completed Rebate, Banned, Inactive. | F98: Completed | G98: Brand Dashboard + Backend / API | H98: — | I98: Customers | J98: Open Customers; check each column and tab against a shopper with an open claim and a cooldown. | M98: #29
B99: 91 | C99: Customer Profile | D99: Header (opt-in badges, status) + Ban Customer with reason | E99: Header: name, contact, customer since, last active, Nibbl Opt-In + brand Opt-In badges, Active/Banned. Ban modal with reason (suspicious activity, altered receipts, abuse, other); banned shoppers can't claim or get review opportunities from the brand; existing claims stay valid. Lift Ban. | F99: Completed | G99: Brand Dashboard + Backend / API | H99: — | I99: Customers → View → Ban Customer | J99: Ban with a reason; status shows Banned with the reason; Lift Ban restores it. | M99: #46
B100: 92 | C100: Customer Profile | D100: Relationship with brand · Nibbl activity totals · Recent activity | E100: Relationship tiles (claims, completed rebates, conversion, rewards, reviews, open claims); Nibbl totals only (claims, completion, reviews, rewards) — other brands' data never shown; recent activity timeline for this brand. | F100: Completed | G100: Brand Dashboard + Backend / API | H100: — | I100: Customers → View | J100: Open a profile; totals match the shopper's history. | M100: #29
B101: 93 | C101: Customer Profile | D101: Open claims · Cooldowns with Remove (confirmation + audit) | E101: Open claims with days left. Rebate and review cooldowns with Remove → confirmation → cooldown cleared and an audit-log entry (who, when, which). Managers only. | F101: Completed | G101: Brand Dashboard + Backend / API | H101: — | I101: Customers → View → Cooldowns → Remove | J101: Remove a cooldown; the shopper can claim/review again; the audit log shows the removal. | M101: #29
B102: 94 | C102: Customer Profile | D102: Redemption history: full receipt 30 days, then matching line only | E102: Redemption history with View receipt + days left for 30 days; afterwards only the matching line item(s) are shown. | F102: Completed | G102: Brand Dashboard + Backend / API | H102: — | I102: Customers → View → Redemption History | J102: Recent receipt shows View receipt; one older than 30 days shows Matching line only. | M102: #29
B103: 95 | C103: Brand Wallet | D103: Balances: Available, Reserved, Promotional (definitions) | E103: As specified. | F103: Completed | G103: Brand Dashboard | H103: — | I103: Wallet | J103: Check balances. | M103: #30
B104: 96 | C104: Brand Wallet | D104: Campaign Funding: 7-day need vs Available, funded status, reservations split | E104: As specified. | F104: Completed | G104: Brand Dashboard | H104: — | I104: Wallet → Campaign Funding | J104: Activate a campaign. | M104: #30
B105: 97 | C105: Brand Wallet | D105: Automatic refill (Stripe): trigger 25%, fixed amount, recommendation, failure alert | E105: As specified. | F105: In Progress | G105: Brand Dashboard + Backend / API | H105: — | I105: Wallet → Auto-refill | J105: Enable auto-refill. | K105: Production still on Stripe test keys — switch to the live keys received from the client, then retest. | M105: #31
...

Sheet Summary by Section
B2: Progress by Master Document Section
B4: Master Document Section | C4: Total | D4: Completed | E4: In Progress | F4: In Review | G4: Planned | H4: Completion
B5: Brand Dashboard Home | C5: =COUNTIF('Master Requirements Tracker'!$C$9:$C$158,B5) -> 8 | D5: =COUNTIFS('Master Requirements Tracker'!$C$9:$C$158,B5,'Master Requirements Tracker'!$F$9:$F$158,"Completed") -> 8 | E5: =COUNTIFS('Master Requirements Tracker'!$C$9:$C$158,B5,'Master Requirements Tracker'!$F$9:$F$158,"In Progress") -> 0 | F5: =COUNTIFS('Master Requirements Tracker'!$C$9:$C$158,B5,'Master Requirements Tracker'!$F$9:$F$158,"In Review") -> 0 | G5: =COUNTIFS('Master Requirements Tracker'!$C$9:$C$158,B5,'Master Requirements Tracker'!$F$9:$F$158,"Planned") -> 0 | H5: =IF(C5>0,D5/C5,0) -> 1
B6: Product Library | C6: =COUNTIF('Master Requirements Tracker'!$C$9:$C$158,B6) -> 10 | D6: =COUNTIFS('Master Requirements Tracker'!$C$9:$C$158,B6,'Master Requirements Tracker'!$F$9:$F$158,"Completed") -> 6 | E6: =COUNTIFS('Master Requirements Tracker'!$C$9:$C$158,B6,'Master Requirements Tracker'!$F$9:$F$158,"In Progress") -> 3 | F6: =COUNTIFS('Master Requirements Tracker'!$C$9:$C$158,B6,'Master Requirements Tracker'!$F$9:$F$158,"In Review") -> 0 | G6: =COUNTIFS('Master Requirements Tracker'!$C$9:$C$158,B6,'Master Requirements Tracker'!$F$9:$F$158,"Planned") -> 1 | H6: =IF(C6>0,D6/C6,0) -> 0.6
B7: Rebate Campaigns List | C7: =COUNTIF('Master Requirements Tracker'!$C$9:$C$158,B7) -> 3 | D7: =COUNTIFS('Master Requirements Tracker'!$C$9:$C$158,B7,'Master Requirements Tracker'!$F$9:$F$158,"Completed") -> 3 | E7: =COUNTIFS('Master Requirements Tracker'!$C$9:$C$158,B7,'Master Requirements Tracker'!$F$9:$F$158,"In Progress") -> 0 | F7: =COUNTIFS('Master Requirements Tracker'!$C$9:$C$158,B7,'Master Requirements Tracker'!$F$9:$F$158,"In Review") -> 0 | G7: =COUNTIFS('Master Requirements Tracker'!$C$9:$C$158,B7,'Master Requirements Tracker'!$F$9:$F$158,"Planned") -> 0 | H7: =IF(C7>0,D7/C7,0) -> 1
B8: Create Rebate Campaign | C8: =COUNTIF('Master Requirements Tracker'!$C$9:$C$158,B8) -> 13 | D8: =COUNTIFS('Master Requirements Tracker'!$C$9:$C$158,B8,'Master Requirements Tracker'!$F$9:$F$158,"Completed") -> 13 | E8: =COUNTIFS('Master Requirements Tracker'!$C$9:$C$158,B8,'Master Requirements Tracker'!$F$9:$F$158,"In Progress") -> 0 | F8: =COUNTIFS('Master Requirements Tracker'!$C$9:$C$158,B8,'Master Requirements Tracker'!$F$9:$F$158,"In Review") -> 0 | G8: =COUNTIFS('Master Requirements Tracker'!$C$9:$C$158,B8,'Master Requirements Tracker'!$F$9:$F$158,"Planned") -> 0 | H8: =IF(C8>0,D8/C8,0) -> 1
B9: Offer Type Inputs & Shopper Output | C9: =COUNTIF('Master Requirements Tracker'!$C$9:$C$158,B9) -> 1 | D9: =COUNTIFS('Master Requirements Tracker'!$C$9:$C$158,B9,'Master Requirements Tracker'!$F$9:$F$158,"Completed") -> 1 | E9: =COUNTIFS('Master Requirements Tracker'!$C$9:$C$158,B9,'Master Requirements Tracker'!$F$9:$F$158,"In Progress") -> 0 | F9: =COUNTIFS('Master Requirements Tracker'!$C$9:$C$158,B9,'Master Requirements Tracker'!$F$9:$F$158,"In Review") -> 0 | G9: =COUNTIFS('Master Requirements Tracker'!$C$9:$C$158,B9,'Master Requirements Tracker'!$F$9:$F$158,"Planned") -> 0 | H9: =IF(C9>0,D9/C9,0) -> 1
B10: Campaign Detail Page | C10: =COUNTIF('Master Requirements Tracker'!$C$9:$C$158,B10) -> 2 | D10: =COUNTIFS('Master Requirements Tracker'!$C$9:$C$158,B10,'Master Requirements Tracker'!$F$9:$F$158,"Completed") -> 2 | E10: =COUNTIFS('Master Requirements Tracker'!$C$9:$C$158,B10,'Master Requirements Tracker'!$F$9:$F$158,"In Progress") -> 0 | F10: =COUNTIFS('Master Requirements Tracker'!$C$9:$C$158,B10,'Master Requirements Tracker'!$F$9:$F$158,"In Review") -> 0 | G10: =COUNTIFS('Master Requirements Tracker'!$C$9:$C$158,B10,'Master Requirements Tracker'!$F$9:$F$158,"Planned") -> 0 | H10: =IF(C10>0,D10/C10,0) -> 1
B11: Effect on Existing Reservations | C11: =COUNTIF('Master Requirements Tracker'!$C$9:$C$158,B11) -> 3 | D11: =COUNTIFS('Master Requirements Tracker'!$C$9:$C$158,B11,'Master Requirements Tracker'!$F$9:$F$158,"Completed") -> 3 | E11: =COUNTIFS('Master Requirements Tracker'!$C$9:$C$158,B11,'Master Requirements Tracker'!$F$9:$F$158,"In Progress") -> 0 | F11: =COUNTIFS('Master Requirements Tracker'!$C$9:$C$158,B11,'Master Requirements Tracker'!$F$9:$F$158,"In Review") -> 0 | G11: =COUNTIFS('Master Requirements Tracker'!$C$9:$C$158,B11,'Master Requirements Tracker'!$F$9:$F$158,"Planned") -> 0 | H11: =IF(C11>0,D11/C11,0) -> 1
B12: Discovery | C12: =COUNTIF('Master Requirements Tracker'!$C$9:$C$158,B12) -> 7 | D12: =COUNTIFS('Master Requirements Tracker'!$C$9:$C$158,B12,'Master Requirements Tracker'!$F$9:$F$158,"Completed") -> 6 | E12: =COUNTIFS('Master Requirements Tracker'!$C$9:$C$158,B12,'Master Requirements Tracker'!$F$9:$F$158,"In Progress") -> 1 | F12: =COUNTIFS('Master Requirements Tracker'!$C$9:$C$158,B12,'Master Requirements Tracker'!$F$9:$F$158,"In Review") -> 0 | G12: =COUNTIFS('Master Requirements Tracker'!$C$9:$C$158,B12,'Master Requirements Tracker'!$F$9:$F$158,"Planned") -> 0 | H12: =IF(C12>0,D12/C12,0) -> 0.85714286
B13: Shopper Rebate Flow | C13: =COUNTIF('Master Requirements Tracker'!$C$9:$C$158,B13) -> 7 | D13: =COUNTIFS('Master Requirements Tracker'!$C$9:$C$158,B13,'Master Requirements Tracker'!$F$9:$F$158,"Completed") -> 5 | E13: =COUNTIFS('Master Requirements Tracker'!$C$9:$C$158,B13,'Master Requirements Tracker'!$F$9:$F$158,"In Progress") -> 2 | F13: =COUNTIFS('Master Requirements Tracker'!$C$9:$C$158,B13,'Master Requirements Tracker'!$F$9:$F$158,"In Review") -> 0 | G13: =COUNTIFS('Master Requirements Tracker'!$C$9:$C$158,B13,'Master Requirements Tracker'!$F$9:$F$158,"Planned") -> 0 | H13: =IF(C13>0,D13/C13,0) -> 0.71428571
B14: Receipt Submission | C14: =COUNTIF('Master Requirements Tracker'!$C$9:$C$158,B14) -> 1 | D14: =COUNTIFS('Master Requirements Tracker'!$C$9:$C$158,B14,'Master Requirements Tracker'!$F$9:$F$158,"Completed") -> 1 | E14: =COUNTIFS('Master Requirements Tracker'!$C$9:$C$158,B14,'Master Requirements Tracker'!$F$9:$F$158,"In Progress") -> 0 | F14: =COUNTIFS('Master Requirements Tracker'!$C$9:$C$158,B14,'Master Requirements Tracker'!$F$9:$F$158,"In Review") -> 0 | G14: =COUNTIFS('Master Requirements Tracker'!$C$9:$C$158,B14,'Master Requirements Tracker'!$F$9:$F$158,"Planned") -> 0 | H14: =IF(C14>0,D14/C14,0) -> 1
B15: Receipt Validation & Routing | C15: =COUNTIF('Master Requirements Tracker'!$C$9:$C$158,B15) -> 2 | D15: =COUNTIFS('Master Requirements Tracker'!$C$9:$C$158,B15,'Master Requirements Tracker'!$F$9:$F$158,"Completed") -> 2 | E15: =COUNTIFS('Master Requirements Tracker'!$C$9:$C$158,B15,'Master Requirements Tracker'!$F$9:$F$158,"In Progress") -> 0 | F15: =COUNTIFS('Master Requirements Tracker'!$C$9:$C$158,B15,'Master Requirements Tracker'!$F$9:$F$158,"In Review") -> 0 | G15: =COUNTIFS('Master Requirements Tracker'!$C$9:$C$158,B15,'Master Requirements Tracker'!$F$9:$F$158,"Planned") -> 0 | H15: =IF(C15>0,D15/C15,0) -> 1
B16: Receipt Outcomes | C16: =COUNTIF('Master Requirements Tracker'!$C$9:$C$158,B16) -> 2 | D16: =COUNTIFS('Master Requirements Tracker'!$C$9:$C$158,B16,'Master Requirements Tracker'!$F$9:$F$158,"Completed") -> 2 | E16: =COUNTIFS('Master Requirements Tracker'!$C$9:$C$158,B16,'Master Requirements Tracker'!$F$9:$F$158,"In Progress") -> 0 | F16: =COUNTIFS('Master Requirements Tracker'!$C$9:$C$158,B16,'Master Requirements Tracker'!$F$9:$F$158,"In Review") -> 0 | G16: =COUNTIFS('Master Requirements Tracker'!$C$9:$C$158,B16,'Master Requirements Tracker'!$F$9:$F$158,"Planned") -> 0 | H16: =IF(C16>0,D16/C16,0) -> 1
... B49: Cross-cutting | C49: =COUNTIF('Master Requirements Tracker'!$C$9:$C$158,B49) -> 3 | D49: =COUNTIFS('Master Requirements Tracker'!$C$9:$C$158,B49,'Master Requirements Tracker'!$F$9:$F$158,"Completed") -> 3 | E49: =COUNTIFS('Master Requirements Tracker'!$C$9:$C$158,B49,'Master Requirements Tracker'!$F$9:$F$158,"In Progress") -> 0 | F49: =COUNTIFS('Master Requirements Tracker'!$C$9:$C$158,B49,'Master Requirements Tracker'!$F$9:$F$158,"In Review") -> 0 | G49: =COUNTIFS('Master Requirements Tracker'!$C$9:$C$158,B49,'Master Requirements Tracker'!$F$9:$F$158,"Planned") -> 0 | H49: =IF(C49>0,D49/C49,0) -> 1
B50: Total | C50: =SUM(C5:C49) -> 150 | D50: =SUM(D5:D49) -> 130 | E50: =SUM(E5:E49) -> 13 | F50: =SUM(F5:F49) -> 2 | G50: =SUM(G5:G49) -> 5 | H50: =IF(C50>0,D50/C50,0) -> 0.86666667

Sheet Open Dependencies
B2: Open Dependencies (outside the development team)
B4: Owner | C4: What's Needed | D4: Current State | E4: Status
B5: Our team — Stripe | C5: Switch production to the live Stripe keys the client sent; retest checkout, top-up and auto-refill | D5: Client moved Stripe to live production (live keys + webhook secret received) | E5: In Progress
B6: Our team — Twilio | C6: Retest SMS-verified withdrawals; lock verified phones (change via admin + history) | D6: Twilio SMS verified on production 12 Oct 2026 (code sent to a Bangladesh number, delivered, approved). Remaining: one real website withdrawal with the SMS step | E6: In Progress
B7: Client — DNS | C7: Cloudflare access for www / brand / admin so the web apps can go live | D7: Done — www / brand / admin.joinnibbl.com live with SSL on 11 Oct 2026 | E7: Completed
B8: AI service (Sakibur) | C8: Adaptive review questions + AI review summary endpoints | D8: docs/AI_REVIEW_ENDPOINTS_SPEC.md shared | E8: In Review
B9: Mobile app developer | C9: App screens for shopper flows; required consents; X-Device-Id; referral progress | D9: Consumer API handover doc updated | E9: In Progress
B10: Client — AWS SES | C10: System email from @joinnibbl.com + bounce/complaint handling | D10: Done — production email switched to SES on 11 Oct 2026 (per the client's 10 Oct credentials doc). Note: the Master says Klaviyo sends system emails — confirm SES is the long-term choice | E10: Completed
B11: Client — Firebase | C11: Push via Workload Identity Federation (EC2 role sent) | D11: Waiting on client setup | E11: Planned
B12: Client — Klaviyo / SMS decision | C12: Master Settings §3: 'Klaviyo will send Nibbl system emails and SMS messages' (Nibbl's internal Klaviyo account). Brand SMS toggles are stored but no SMS is sent yet | D12: Decision needed: Klaviyo access (private API key + SMS sender) as the Master says, or use the existing Twilio account for brand SMS | E12: In Review
B13: Client — FAQ content | C13: Brand homepage 'Questions?' strip (Master mockup ④ only): Pricing / Review campaigns / Account & billing / General FAQ | D13: No FAQ content in the Master — need questions/answers or a help-centre link; shown as labels until then | E13: In Review

Sheet How to Use
B2: How to Use This Tracker
B4: Rows | C4: One row per requirement, in the Master Document's order, including the requirements shown only in the Master's screenshots. The Master stays the final source of truth. 'Checklist Ref' links to our internal 51-item checklist.
B5: Completed | C5: The full requirement works as intended, has been tested end to end and can be demonstrated. If any required sub-feature is missing, the row stays In Progress.
B6: In Progress | C6: Partly built. 'Open Items / Notes' says exactly what is still missing.
B7: In Review | C7: Our part is ready; waiting on a third party (e.g. the AI service endpoint or the client's Firebase setup).
B8: Planned | C8: Not built yet.
B9: Where to See It | C9: Screen path in the app. Brand Dashboard = brand.joinnibbl.com, Admin = admin.joinnibbl.com, Shopper Website = www.joinnibbl.com once the web apps are deployed (waiting on DNS); until then they run as a testable build against the live API.
B10: How to Test | C10: Short steps to see the requirement working. Use test accounts. Production still runs Stripe in test mode (card 4242 4242 4242 4242) until we switch to the live keys — see Open Dependencies.
B11: Evidence | C11: Yellow cells — paste a screenshot or screen-recording link (e.g. Loom / Google Drive) for each row as it's demonstrated.
B12: Mobile App | C12: Shopper rows show 'API ready — app developer to build/confirm': the backend is done and documented; the app developer builds the screen in the mobile app. '—' means not an app screen.
B13: Status column | C13: Pick from the dropdown; the totals at the top and the 'Summary by Section' sheet update automatically.
